filesync/filesync.py
filesync/progess.py
filesync-0.1.3.dist-info/LICENSE
filesync-0.1.3.dist-info/METADATA
filesync-0.1.3.dist-info/WHEEL
filesync-0.1.3.dist-info/entry_points.txt
filesync-0.1.3.dist-info/top_level.txt
filesync-0.1.3.dist-info/RECORD
